phoenix_letter/__init__.py
phoenix_letter/main.py
phoenix_letter/version.py
phoenix_letter/common/__init__.py
phoenix_letter/common/arguments.py
phoenix_letter/common/credentials.py
phoenix_letter/common/enums.py
phoenix_letter-0.3.7.dist-info/LICENSE
phoenix_letter-0.3.7.dist-info/METADATA
phoenix_letter-0.3.7.dist-info/WHEEL
phoenix_letter-0.3.7.dist-info/entry_points.txt
phoenix_letter-0.3.7.dist-info/top_level.txt
phoenix_letter-0.3.7.dist-info/RECORD
