Metadata-Version: 2.1
Name: phoenix-letter
Version: 0.3.7
Summary: CLI to move messages from a AWS SQS Queue to another
Home-page: https://github.com/renanvieira/phoenix-letter
Author: Renan Vieira
Author-email: me@renanvieira.net
License: MIT
Keywords: AWS,SQS,Queue,DLQ,Dead,Letter,Queue
Classifier: Development Status :: 4 - Beta
Classifier: Intended Audience :: Developers
Classifier: Topic :: Software Development
Classifier: License :: OSI Approved :: MIT License
Classifier: Programming Language :: Python :: 3.7
Classifier: Programming Language :: Python :: 3.8
Classifier: Programming Language :: Python :: 3.9
Classifier: Programming Language :: Python :: 3.10
Classifier: Programming Language :: Python :: 3.11
Requires-Python: >=3.7
License-File: LICENSE
Requires-Dist: boto3
Requires-Dist: six
